Workbook
Name CustomerIDs: Customer_Lookup!$A$2:$A$17
Name CustomerNames: Customer_Lookup!$B$2:$B$17
Name PracticeCategory: Transactions!$M$2:$M$31
Name PracticeProfit: Transactions!$S$2:$S$31
Name PracticeRegion: Transactions!$K$2:$K$31
Name PracticeSales: Transactions!$P$2:$P$31
Name ProductCategories: Product_Lookup!$C$2:$C$31
Name ProductIDs: Product_Lookup!$A$2:$A$31

Sheet Transactions
A1: Row ID | B1: Order ID | C1: Order Date | D1: Ship Date | E1: Ship Mode | F1: Customer ID | G1: Customer Name | H1: Segment | I1: City | J1: State/Province | K1: Region | L1: Product ID | M1: Category | N1: Sub-Category | O1: Product Name | P1: Sales | Q1: Quantity | R1: Discount | S1: Profit | T1: Profit Status | U1: Sales Band | V1: Order Year | W1: Order Month | X1: Order Prefix | Y1: Order Year Code | Z1: Order Suffix | AA1: Customer Name Length | AB1: Clean Customer Name | AC1: Region Flag
A2: 1 | B2: US-2023-103800 | C2: 44929 | D2: 44933 | E2: Standard Class | F2: DP-13000 | G2: Darren Powers | H2: Consumer | I2: Houston | J2: Texas | K2: Central | L2: OFF-PA-10000174 | M2: Office Supplies | N2: Paper | O2: Message Book, Wirebound, Four 5 1/2" X 4" Forms/Pg., 200 Dupl. Sets/Book | P2: 16.448 | Q2: 2 | R2: 0.2 | S2: 5.5512 | T2: =IF(S2>=0,"Profit","Loss") -> Profit | U2: =IF(P2>=500,"High Value",IF(P2>=100,"Medium Value","Low Value")) -> Low Value | V2: =YEAR(C2) -> 2023 | W2: =TEXT(C2,"mmm") -> Jan | X2: =LEFT(B2,2) -> US | Y2: =MID(B2,4,4) -> 2023 | Z2: =RIGHT(B2,6) -> 103800 | AA2: =LEN(G2) -> 13 | AB2: =TRIM(G2) -> Darren Powers | AC2: =IF(K2="West","Priority Region","Standard Region") -> Standard Region
A3: 2 | B3: US-2023-112326 | C3: 44930 | D3: 44934 | E3: Standard Class | F3: PO-19195 | G3: Phillina Ober | H3: Home Office | I3: Naperville | J3: Illinois | K3: Central | L3: OFF-BI-10004094 | M3: Office Supplies | N3: Binders | O3: GBC Standard Plastic Binding Systems Combs | P3: 3.54 | Q3: 2 | R3: 0.8 | S3: -5.487 | T3: =IF(S3>=0,"Profit","Loss") -> Loss | U3: =IF(P3>=500,"High Value",IF(P3>=100,"Medium Value","Low Value")) -> Low Value | V3: =YEAR(C3) -> 2023 | W3: =TEXT(C3,"mmm") -> Jan | X3: =LEFT(B3,2) -> US | Y3: =MID(B3,4,4) -> 2023 | Z3: =RIGHT(B3,6) -> 112326 | AA3: =LEN(G3) -> 13 | AB3: =TRIM(G3) -> Phillina Ober | AC3: =IF(K3="West","Priority Region","Standard Region") -> Standard Region
A4: 3 | B4: US-2023-112326 | C4: 44930 | D4: 44934 | E4: Standard Class | F4: PO-19195 | G4: Phillina Ober | H4: Home Office | I4: Naperville | J4: Illinois | K4: Central | L4: OFF-LA-10003223 | M4: Office Supplies | N4: Labels | O4: Avery 508 | P4: 11.784 | Q4: 3 | R4: 0.2 | S4: 4.2717 | T4: =IF(S4>=0,"Profit","Loss") -> Profit | U4: =IF(P4>=500,"High Value",IF(P4>=100,"Medium Value","Low Value")) -> Low Value | V4: =YEAR(C4) -> 2023 | W4: =TEXT(C4,"mmm") -> Jan | X4: =LEFT(B4,2) -> US | Y4: =MID(B4,4,4) -> 2023 | Z4: =RIGHT(B4,6) -> 112326 | AA4: =LEN(G4) -> 13 | AB4: =TRIM(G4) -> Phillina Ober | AC4: =IF(K4="West","Priority Region","Standard Region") -> Standard Region
A5: 4 | B5: US-2023-112326 | C5: 44930 | D5: 44934 | E5: Standard Class | F5: PO-19195 | G5: Phillina Ober | H5: Home Office | I5: Naperville | J5: Illinois | K5: Central | L5: OFF-ST-10002743 | M5: Office Supplies | N5: Storage | O5: SAFCO Boltless Steel Shelving | P5: 272.736 | Q5: 3 | R5: 0.2 | S5: -64.7748 | T5: =IF(S5>=0,"Profit","Loss") -> Loss | U5: =IF(P5>=500,"High Value",IF(P5>=100,"Medium Value","Low Value")) -> Medium Value | V5: =YEAR(C5) -> 2023 | W5: =TEXT(C5,"mmm") -> Jan | X5: =LEFT(B5,2) -> US | Y5: =MID(B5,4,4) -> 2023 | Z5: =RIGHT(B5,6) -> 112326 | AA5: =LEN(G5) -> 13 | AB5: =TRIM(G5) -> Phillina Ober | AC5: =IF(K5="West","Priority Region","Standard Region") -> Standard Region
A6: 5 | B6: US-2023-141817 | C6: 44931 | D6: 44938 | E6: Standard Class | F6: MB-18085 | G6: Mick Brown | H6: Consumer | I6: Philadelphia | J6: Pennsylvania | K6: East | L6: OFF-AR-10003478 | M6: Office Supplies | N6: Art | O6: Avery Hi-Liter EverBold Pen Style Fluorescent Highlighters, 4/Pack | P6: 19.536 | Q6: 3 | R6: 0.2 | S6: 4.884 | T6: =IF(S6>=0,"Profit","Loss") -> Profit | U6: =IF(P6>=500,"High Value",IF(P6>=100,"Medium Value","Low Value")) -> Low Value | V6: =YEAR(C6) -> 2023 | W6: =TEXT(C6,"mmm") -> Jan | X6: =LEFT(B6,2) -> US | Y6: =MID(B6,4,4) -> 2023 | Z6: =RIGHT(B6,6) -> 141817 | AA6: =LEN(G6) -> 10 | AB6: =TRIM(G6) -> Mick Brown | AC6: =IF(K6="West","Priority Region","Standard Region") -> Standard Region
A7: 6 | B7: US-2023-167199 | C7: 44932 | D7: 44936 | E7: Standard Class | F7: ME-17320 | G7: Maria Etezadi | H7: Home Office | I7: Henderson | J7: Kentucky | K7: South | L7: FUR-CH-10004063 | M7: Furniture | N7: Chairs | O7: Global Deluxe High-Back Manager's Chair | P7: 2573.82 | Q7: 9 | R7: 0 | S7: 746.4078 | T7: =IF(S7>=0,"Profit","Loss") -> Profit | U7: =IF(P7>=500,"High Value",IF(P7>=100,"Medium Value","Low Value")) -> High Value | V7: =YEAR(C7) -> 2023 | W7: =TEXT(C7,"mmm") -> Jan | X7: =LEFT(B7,2) -> US | Y7: =MID(B7,4,4) -> 2023 | Z7: =RIGHT(B7,6) -> 167199 | AA7: =LEN(G7) -> 13 | AB7: =TRIM(G7) -> Maria Etezadi | AC7: =IF(K7="West","Priority Region","Standard Region") -> Standard Region
A8: 7 | B8: US-2023-167199 | C8: 44932 | D8: 44936 | E8: Standard Class | F8: ME-17320 | G8: Maria Etezadi | H8: Home Office | I8: Henderson | J8: Kentucky | K8: South | L8: OFF-AR-10001662 | M8: Office Supplies | N8: Art | O8: Rogers Handheld Barrel Pencil Sharpener | P8: 5.48 | Q8: 2 | R8: 0 | S8: 1.4796 | T8: =IF(S8>=0,"Profit","Loss") -> Profit | U8: =IF(P8>=500,"High Value",IF(P8>=100,"Medium Value","Low Value")) -> Low Value | V8: =YEAR(C8) -> 2023 | W8: =TEXT(C8,"mmm") -> Jan | X8: =LEFT(B8,2) -> US | Y8: =MID(B8,4,4) -> 2023 | Z8: =RIGHT(B8,6) -> 167199 | AA8: =LEN(G8) -> 13 | AB8: =TRIM(G8) -> Maria Etezadi | AC8: =IF(K8="West","Priority Region","Standard Region") -> Standard Region
A9: 21 | B9: US-2023-130092 | C9: 44937 | D9: 44940 | E9: First Class | F9: SV-20365 | G9: Seth Vernon | H9: Consumer | I9: Dover | J9: Delaware | K9: East | L9: FUR-FU-10000010 | M9: Furniture | N9: Furnishings | O9: DAX Value U-Channel Document Frames, Easel Back | P9: 9.94 | Q9: 2 | R9: 0 | S9: 3.0814 | T9: =IF(S9>=0,"Profit","Loss") -> Profit | U9: =IF(P9>=500,"High Value",IF(P9>=100,"Medium Value","Low Value")) -> Low Value | V9: =YEAR(C9) -> 2023 | W9: =TEXT(C9,"mmm") -> Jan | X9: =LEFT(B9,2) -> US | Y9: =MID(B9,4,4) -> 2023 | Z9: =RIGHT(B9,6) -> 130092 | AA9: =LEN(G9) -> 11 | AB9: =TRIM(G9) -> Seth Vernon | AC9: =IF(K9="West","Priority Region","Standard Region") -> Standard Region
A10: 22 | B10: US-2023-157147 | C10: 44939 | D10: 44944 | E10: Standard Class | F10: BD-11605 | G10: Brian Dahlen | H10: Consumer | I10: San Francisco | J10: California | K10: West | L10: FUR-BO-10003034 | M10: Furniture | N10: Bookcases | O10: O'Sullivan Elevations Bookcase, Cherry Finish | P10: 333.999 | Q10: 3 | R10: 0.15 | S10: 3.9294 | T10: =IF(S10>=0,"Profit","Loss") -> Profit | U10: =IF(P10>=500,"High Value",IF(P10>=100,"Medium Value","Low Value")) -> Medium Value | V10: =YEAR(C10) -> 2023 | W10: =TEXT(C10,"mmm") -> Jan | X10: =LEFT(B10,2) -> US | Y10: =MID(B10,4,4) -> 2023 | Z10: =RIGHT(B10,6) -> 157147 | AA10: =LEN(G10) -> 12 | AB10: =TRIM(G10) -> Brian Dahlen | AC10: =IF(K10="West","Priority Region","Standard Region") -> Priority Region
A11: 23 | B11: US-2023-109232 | C11: 44939 | D11: 44942 | E11: Second Class | F11: ND-18370 | G11: Natalie DeCherney | H11: Consumer | I11: Mount Pleasant | J11: South Carolina | K11: South | L11: FUR-CH-10000422 | M11: Furniture | N11: Chairs | O11: Global Highback Leather Tilter in Burgundy | P11: 545.94 | Q11: 6 | R11: 0 | S11: 87.3504 | T11: =IF(S11>=0,"Profit","Loss") -> Profit | U11: =IF(P11>=500,"High Value",IF(P11>=100,"Medium Value","Low Value")) -> High Value | V11: =YEAR(C11) -> 2023 | W11: =TEXT(C11,"mmm") -> Jan | X11: =LEFT(B11,2) -> US | Y11: =MID(B11,4,4) -> 2023 | Z11: =RIGHT(B11,6) -> 109232 | AA11: =LEN(G11) -> 17 | AB11: =TRIM(G11) -> Natalie DeCherney | AC11: =IF(K11="West","Priority Region","Standard Region") -> Standard Region
A12: 24 | B12: US-2023-157147 | C12: 44939 | D12: 44944 | E12: Standard Class | F12: BD-11605 | G12: Brian Dahlen | H12: Consumer | I12: San Francisco | J12: California | K12: West | L12: OFF-AR-10003514 | M12: Office Supplies | N12: Art | O12: 4009 Highlighters by Sanford | P12: 19.9 | Q12: 5 | R12: 0 | S12: 6.567 | T12: =IF(S12>=0,"Profit","Loss") -> Profit | U12: =IF(P12>=500,"High Value",IF(P12>=100,"Medium Value","Low Value")) -> Low Value | V12: =YEAR(C12) -> 2023 | W12: =TEXT(C12,"mmm") -> Jan | X12: =LEFT(B12,2) -> US | Y12: =MID(B12,4,4) -> 2023 | Z12: =RIGHT(B12,6) -> 157147 | AA12: =LEN(G12) -> 12 | AB12: =TRIM(G12) -> Brian Dahlen | AC12: =IF(K12="West","Priority Region","Standard Region") -> Priority Region
A13: 25 | B13: US-2023-118192 | C13: 44939 | D13: 44944 | E13: Standard Class | F13: MM-17920 | G13: Michael Moore | H13: Consumer | I13: Newark | J13: Ohio | K13: East | L13: OFF-BI-10003476 | M13: Office Supplies | N13: Binders | O13: Avery Metallic Poly Binders | P13: 3.438 | Q13: 2 | R13: 0.7 | S13: -2.5212 | T13: =IF(S13>=0,"Profit","Loss") -> Loss | U13: =IF(P13>=500,"High Value",IF(P13>=100,"Medium Value","Low Value")) -> Low Value | V13: =YEAR(C13) -> 2023 | W13: =TEXT(C13,"mmm") -> Jan | X13: =LEFT(B13,2) -> US | Y13: =MID(B13,4,4) -> 2023 | Z13: =RIGHT(B13,6) -> 118192 | AA13: =LEN(G13) -> 13 | AB13: =TRIM(G13) -> Michael Moore | AC13: =IF(K13="West","Priority Region","Standard Region") -> Standard Region
... A31: 168 | B31: US-2023-156587 | C31: 44992 | D31: 44993 | E31: First Class | F31: AB-10015 | G31: Aaron Bergman | H31: Consumer | I31: Seattle | J31: Washington | K31: West | L31: OFF-ST-10002344 | M31: Office Supplies | N31: Storage | O31: Carina 42"Hx23 3/4"W Media Storage Unit | P31: 242.94 | Q31: 3 | R31: 0 | S31: 4.8588 | T31: =IF(S31>=0,"Profit","Loss") -> Profit | U31: =IF(P31>=500,"High Value",IF(P31>=100,"Medium Value","Low Value")) -> Medium Value | V31: =YEAR(C31) -> 2023 | W31: =TEXT(C31,"mmm") -> Mar | X31: =LEFT(B31,2) -> US | Y31: =MID(B31,4,4) -> 2023 | Z31: =RIGHT(B31,6) -> 156587 | AA31: =LEN(G31) -> 13 | AB31: =TRIM(G31) -> Aaron Bergman | AC31: =IF(K31="West","Priority Region","Standard Region") -> Priority Region

Sheet Customer_Lookup
A1: Customer ID | B1: Customer Name | C1: Segment | D1: Region
A2: AB-10015 | B2: Aaron Bergman | C2: Consumer | D2: West
A3: AB-10150 | B3: Aimee Bixby | C3: Consumer | D3: East
A4: AJ-10945 | B4: Ashley Jarboe | C4: Consumer | D4: South
A5: AP-10720 | B5: Anne Pryor | C5: Home Office | D5: East
A6: BD-11605 | B6: Brian Dahlen | C6: Consumer | D6: West
A7: CM-12715 | B7: Craig Molinari | C7: Corporate | D7: West
A8: CS-12250 | B8: Chris Selesnick | C8: Corporate | D8: South
A9: DP-13000 | B9: Darren Powers | C9: Consumer | D9: Central
A10: JS-15595 | B10: Jill Stevenson | C10: Corporate | D10: East
A11: MB-18085 | B11: Mick Brown | C11: Consumer | D11: East
A12: ME-17320 | B12: Maria Etezadi | C12: Home Office | D12: South
... A17: SV-20365 | B17: Seth Vernon | C17: Consumer | D17: East

Sheet Product_Lookup
A1: Product ID | B1: Product Name | C1: Category | D1: Sub-Category
A2: FUR-BO-10003034 | B2: O'Sullivan Elevations Bookcase, Cherry Finish | C2: Furniture | D2: Bookcases
A3: FUR-CH-10000422 | B3: Global Highback Leather Tilter in Burgundy | C3: Furniture | D3: Chairs
A4: FUR-CH-10002780 | B4: Office Star - Task Chair with Contemporary Loop Arms | C4: Furniture | D4: Chairs
A5: FUR-CH-10004063 | B5: Global Deluxe High-Back Manager's Chair | C5: Furniture | D5: Chairs
A6: FUR-CH-10004477 | B6: Global Push Button Manager's Chair, Indigo | C6: Furniture | D6: Chairs
A7: FUR-CH-10004495 | B7: Global Leather and Oak Executive Chair, Black | C7: Furniture | D7: Chairs
A8: FUR-FU-10000010 | B8: DAX Value U-Channel Document Frames, Easel Back | C8: Furniture | D8: Furnishings
A9: OFF-AP-10002534 | B9: 3.6 Cubic Foot Counter Height Office Refrigerator | C9: Office Supplies | D9: Appliances
A10: OFF-AR-10000390 | B10: Newell Chalk Holder | C10: Office Supplies | D10: Art
A11: OFF-AR-10001662 | B11: Rogers Handheld Barrel Pencil Sharpener | C11: Office Supplies | D11: Art
A12: OFF-AR-10003478 | B12: Avery Hi-Liter EverBold Pen Style Fluorescent Highlighters, 4/Pack | C12: Office Supplies | D12: Art
... A31: TEC-AC-10002001 | B31: Logitech Wireless Gaming Headset G930 | C31: Technology | D31: Accessories

Sheet Formula_Demo
A1: Formula Demonstration — Live Excel Formulas
A3: Function / Task | B3: Input / Criteria | C3: Live Excel Formula | D3: Expected Result | E3: When to Use | F3: Edge-Case / Analyst Note
A4: VLOOKUP | B4: DP-13000 | C4: =VLOOKUP(B4,Customer_Lookup!$A$2:$D$17,2,FALSE) -> Darren Powers | D4: Darren Powers | E4: Exact match lookup from Customer_Lookup. | F4: Exact match is safer for IDs. Avoid approximate match unless the lookup table is sorted.
A5: XLOOKUP | B5: OFF-PA-10000174 | C5: =XLOOKUP(B5,Product_Lookup!$A$2:$A$31,Product_Lookup!$C$2:$C$31,"Not Found") -> #NAME? | D5: Office Supplies | E5: Modern exact lookup; returns Not Found for a missing key. | F5: Returns 'Not Found' instead of an Excel error for a missing key.
A6: IF | B6: Profit check | C6: =IF(Transactions!S2>=0,"Profit","Loss") -> Profit | D6: Profit | E6: Create business labels from a logical condition. | F6: Test boundary values such as exactly 0.
A7: SUMIF | B7: Office Supplies | C7: =SUMIF(Transactions!$M$2:$M$31,B7,Transactions!$P$2:$P$31) -> 1509.12 | D7: 1509.12 | E7: Aggregate one numeric measure using one criterion. | F7: Criteria text must match the source category exactly.
A8: SUMIFS | B8: West | C8: =SUMIFS(Transactions!$P$2:$P$31,Transactions!$K$2:$K$31,B8,Transactions!$M$2:$M$31,"Office Supplies") -> 596.038 | D8: 596.04 | E8: Aggregate a measure using multiple criteria. | F8: Check each criterion range has the same size as the sum range.
A9: COUNTIF | B9: Consumer | C9: =COUNTIF(Transactions!$H$2:$H$31,B9) -> 14 | D9: 14 | E9: Count rows matching one condition. | F9: Text criteria are case-insensitive but must otherwise match the intended label.
A10: COUNTIFS | B10: Discount >= 70% and Profit < 0 | C10: =COUNTIFS(Transactions!$R$2:$R$31,">=70%",Transactions!$S$2:$S$31,"<0") -> 3 | D10: 3 | E10: Count transactions satisfying multiple business conditions. | F10: Useful for exception monitoring and quality checks.
A11: LEFT | B11: Order ID prefix | C11: =LEFT(Transactions!B2,2) -> US | D11: US | E11: Extract characters from the left side of IDs or codes. | F11: Do not assume a fixed pattern unless the source standard is known.
A12: MID | B12: Order year from Order ID | C12: =MID(Transactions!B2,4,4) -> 2023 | D12: 2023 | E12: Extract a fixed-position segment from a text identifier. | F12: Position-based extraction breaks if the ID format changes.
A13: RIGHT | B13: Order ID numeric suffix | C13: =RIGHT(Transactions!B2,6) -> 103800 | D13: 103800 | E13: Extract characters from the right side of IDs. | F13: Use only when the suffix length is consistent.
A14: LEN | B14: Customer name length | C14: =LEN(Transactions!G2) -> 13 | D14: 13 | E14: Measure text length for validation or profiling. | F14: Spaces count as characters.
A15: TRIM | B15: Remove extra spaces | C15: =TRIM(" Data Analyst ") -> Data Analyst | D15: Data Analyst | E15: Clean accidental leading, trailing, or repeated spaces. | F15: TRIM does not remove every kind of non-breaking space.
A16: INDEX/MATCH | B16: DP-13000 | C16: =INDEX(Customer_Lookup!$B$2:$B$17,MATCH(B16,Customer_Lookup!$A$2:$A$17,0)) -> Darren Powers | D16: Darren Powers | E16: Useful when you want a flexible lookup pattern and for compatibility with older Excel versions. | F16: MATCH with 0 performs exact matching.
A17: IFERROR + XLOOKUP | B17: Invalid Customer ID | C17: =IFERROR(XLOOKUP("ZZ-99999",Customer_Lookup!$A$2:$A$17,Customer_Lookup!$B$2:$B$17),"Not Found") -> Not Found | D17: Not Found | E17: Gracefully handle missing lookup results. | F17: Useful in production workbooks where missing keys are expected.

Sheet Summary
A1: Task 6 Formula Practice — Summary
A3: Metric | B3: Calculated Value | C3: Excel Formula / Method | D3: Interpretation | F3: Task requirement coverage
A4: Practice rows | B4: 30 | C4: =COUNTA(Transactions!A2:A31) -> 30 | D4: Number of transactional records used for this task. | F4: VLOOKUP | G4: Completed
A5: Unique customers | B5: 16 | C5: =SUMPRODUCT(1/COUNTIF(Transactions!F2:F31,Transactions!F2:F31)) -> 16 | D5: Distinct customer IDs represented in the practice extract. | F5: XLOOKUP | G5: Completed
A6: Total sales in practice extract | B6: 6419.773 | C6: =SUM(PracticeSales) -> 6419.773 | D6: Revenue represented by the selected practice rows. | F6: IF | G6: Completed
A7: Total profit in practice extract | B7: 766.0812 | C7: =SUM(PracticeProfit) -> 766.0812 | D7: Profit after the source dataset's recorded discounts/costs. | F7: SUMIF / SUMIFS | G7: Completed
A8: Average discount | B8: 0.16833333 | C8: =AVERAGE(Transactions!R2:R31) -> 0.16833333 | D8: Mean discount across practice transactions. | F8: COUNTIF / COUNTIFS | G8: Completed
A9: Loss transactions | B9: 5 | C9: =COUNTIF(Transactions!T2:T31,"Loss") -> 5 | D9: Rows where Profit is below zero. | F9: Text functions | G9: LEFT / MID / RIGHT / LEN / TRIM
A10: High-discount transactions (>=70%) | B10: 3 | C10: =COUNTIF(Transactions!R2:R31,">=70%") -> 3 | D10: Rows with unusually high discount values. | F10: Named ranges | G10: Completed
A11: West sales | B11: 1897.021 | C11: =SUMIF(PracticeRegion,"West",PracticeSales) -> 1897.021 | D11: Sales contribution from the West region in the practice extract. | F11: Edge cases | G11: Completed
A14: Region | B14: Sales
A15: Central | B15: 481.28
A16: East | B16: 840.196
A17: South | B17: 3201.276
A18: West | B18: 1897.021

Sheet Validation
A1: Formula Validation & Edge Cases
A3: Test | B3: Purpose | C3: Test Input | D3: Expected | E3: Excel Formula | F3: Status
A4: Valid VLOOKUP | B4: Verify exact customer match | C4: DP-13000 | D4: Darren Powers | E4: =VLOOKUP(C4,Customer_Lookup!$A$2:$D$17,2,FALSE) -> Darren Powers | F4: PASS
A5: Invalid XLOOKUP | B5: Missing key should not break workbook | C5: ZZ-99999 | D5: Not Found | E5: =IFERROR(XLOOKUP(C5,Customer_Lookup!$A$2:$A$17,Customer_Lookup!$B$2:$B$17),"Not Found") -> Not Found | F5: PASS
A6: High discount + loss | B6: Exception count | C6: >=70% discount & <0 profit | D6: 3 | E6: =COUNTIFS(Transactions!$R$2:$R$31,">=70%",Transactions!$S$2:$S$31,"<0") -> 3 | F6: PASS
A7: Text extraction | B7: Validate Order ID pattern | C7: US-2023-103800 | D7: 2023 | E7: =MID(Transactions!B2,4,4) -> 2023 | F7: PASS
A8: Blank lookup note | B8: Document blank-key handling | C8: Blank | D8: Use IF/IFERROR around lookup | E8: See Formula_Demo | F8: PASS
